disposable_mail_checker/__init__.py
disposable_mail_checker/disposable_domains.json
disposable_mail_checker-1.0.dist-info/LICENCE.txt
disposable_mail_checker-1.0.dist-info/METADATA
disposable_mail_checker-1.0.dist-info/WHEEL
disposable_mail_checker-1.0.dist-info/top_level.txt
disposable_mail_checker-1.0.dist-info/RECORD
