Metadata-Version: 2.1
Name: disposable-mail-checker
Version: 1.0
Summary: Check if an email address uses a disposable domain
Home-page: https://github.com/CodemonkHQ/disposable-mail-checker
Author: Codemonk
Author-email: devansh.jha@codemonk.in
License: UNKNOWN
Platform: UNKNOWN
Classifier: Development Status :: 3 - Alpha
Classifier: Intended Audience :: Developers
Classifier: License :: OSI Approved :: MIT License
Classifier: Programming Language :: Python :: 3
License-File: LICENCE.txt
